{"cameraMode":{"drawMode":0,"name":"Shaded","section":"Shading Mode"},"sceneLighting":true,"audioPlay":false,"sceneViewState":{"m_AlwaysRefresh":false,"showFog":true,"showSkybox":true,"showFlares":true,"showImageEffects":true,"showParticleSystems":true,"showVisualEffectGraphs":true,"m_FxEnabled":false},"in2DMode":false,"pivot":{"x":-84.4427261352539,"y":-19.330913543701173,"z":52.92087936401367},"rotation":{"x":-0.10471893846988678,"y":0.7552932500839233,"z":-0.12462282180786133,"w":-0.634917676448822},"size":94.01318359375,"orthographic":false}